{
  "updatedAt": "2026-03-11T23:10:51.370436",
  "totalMarkets": 2,
  "markets": [
    {
      "id": "1227361",
      "slug": "will-iran-close-the-strait-of-hormuz-by-march-31",
      "question": "Will Iran close the Strait of Hormuz by March 31?",
      "description": "If Iran halts or severely restricts international maritime traffic through the Strait of Hormuz by March 31, 2026, 11:59 PM ET, this market will resolve to \"Yes\". Otherwise, this market will resolve t...",
      "conditionId": "0x561cd8d035bac38ed04e23d7882a126da38d7ead9d6679f722ad62c0c9d54ad2",
      "outcomes": [
        "Yes",
        "No"
      ],
      "probabilities": [
        {
          "outcome": "Yes",
          "price": 0.9975,
          "probability": 99.75
        },
        {
          "outcome": "No",
          "price": 0.0025,
          "probability": 0.25
        }
      ],
      "consensus": "Yes (99.75%)",
      "volume": "31757979.862473898",
      "volumeNum": 31757979.862473898,
      "liquidity": "1545162.53336",
      "liquidityNum": 1545162.53336,
      "endDate": "2026-12-31T00:00:00Z",
      "startDate": "2026-01-20T13:35:44.854447Z",
      "active": true,
      "closed": false,
      "clobTokenIds": [
        "11259214629259962188961658360673801608680858594287954976598964541495296876564",
        "50005952796518586292778222685298750447930027597009327781466731324939399757427"
      ],
      "image": "https://polymarket-upload.s3.us-east-2.amazonaws.com/will-iran-close-the-strait-of-hormuz-in-2025-8Ws7O_Z5D_TX.jpg",
      "updatedAt": "2026-03-11T23:10:44.725942"
    },
    {
      "id": "1227362",
      "slug": "will-iran-close-the-strait-of-hormuz-by-june-30",
      "question": "Will Iran close the Strait of Hormuz by June 30?",
      "description": "If Iran halts or severely restricts international maritime traffic through the Strait of Hormuz by June 30, 2026, 11:59 PM ET, this market will resolve to \"Yes\". Otherwise, this market will resolve to...",
      "conditionId": "0x43c7e8f73e867ebc035edf002617f67cf96b90c85eccac18090e553bfe7a8411",
      "outcomes": [
        "Yes",
        "No"
      ],
      "probabilities": [
        {
          "outcome": "Yes",
          "price": 0.9975,
          "probability": 99.75
        },
        {
          "outcome": "No",
          "price": 0.0025,
          "probability": 0.25
        }
      ],
      "consensus": "Yes (99.75%)",
      "volume": "3104100.0782719874",
      "volumeNum": 3104100.0782719874,
      "liquidity": "687553.96931",
      "liquidityNum": 687553.96931,
      "endDate": "2026-06-30T00:00:00Z",
      "startDate": "2026-01-20T13:35:41.813692Z",
      "active": true,
      "closed": false,
      "clobTokenIds": [
        "96553364970466373803947573971182456872615857518046435760618204033520963141265",
        "53537120903759872971668408157792682159334587841332604707736843092565813522797"
      ],
      "image": "https://polymarket-upload.s3.us-east-2.amazonaws.com/will-iran-close-the-strait-of-hormuz-in-2025-8Ws7O_Z5D_TX.jpg",
      "updatedAt": "2026-03-11T23:10:44.961681"
    }
  ]
}